Metadata-Version: 2.1
Name: avro
Version: 1.11.5
Summary: Avro is a serialization and RPC framework.
Home-page: https://avro.apache.org/
Author: Apache Avro
Author-email: dev@avro.apache.org
License: Apache License 2.0
Keywords: avro,serialization,rpc
Classifier: License :: OSI Approved :: Apache Software License
Classifier: Programming Language :: Python :: 3.6
Classifier: Programming Language :: Python :: 3.7
Classifier: Programming Language :: Python :: 3.8
Classifier: Programming Language :: Python :: 3.9
Classifier: Programming Language :: Python :: 3.10
Classifier: Programming Language :: Python :: 3.11
Classifier: Development Status :: 5 - Production/Stable
Requires-Python: >=3.6
License-File: avro/LICENSE
Requires-Dist: typing-extensions; python_version < "3.8"
Provides-Extra: snappy
Requires-Dist: python-snappy; extra == "snappy"
Provides-Extra: zstandard
Requires-Dist: zstandard; extra == "zstandard"
